safeslm/__init__.py
safeslm/cli.py
safeslm/config.py
safeslm/core.py
safeslm/modeling.py
safeslm/pipeline.py
safeslm/routing.py
safeslm/test.py
safeslm/trainer.py
safeslm/trainer_backup.py
safeslm/utils.py
safeslm-0.1.1.dist-info/licenses/LICENSE
safeslm-0.1.1.dist-info/METADATA
safeslm-0.1.1.dist-info/WHEEL
safeslm-0.1.1.dist-info/entry_points.txt
safeslm-0.1.1.dist-info/top_level.txt
safeslm-0.1.1.dist-info/RECORD
