Metadata-Version: 2.4
Name: safeslm
Version: 0.1.1
Summary: SafesLM — safe LLM routing with LoRA adapters
Author-email: Shubham Aggarwal <shubham_agg@alumni.iitm.ac.in>
License: MIT
Requires-Python: >=3.8
License-File: LICENSE
Requires-Dist: transformers>=4.30.0
Requires-Dist: accelerate>=0.20.0
Requires-Dist: torch>=1.13.0
Requires-Dist: datasets>=2.0.0
Requires-Dist: bitsandbytes>=0.48.0
Requires-Dist: peft>=0.4.0
Requires-Dist: tqdm
Requires-Dist: trl
Dynamic: license-file
